odoo/addons/account_global_discount/README.rst
odoo/addons/account_global_discount/__init__.py
odoo/addons/account_global_discount/__manifest__.py
odoo/addons/account_global_discount/hooks.py
odoo/addons/account_global_discount/i18n/.empty
odoo/addons/account_global_discount/i18n/account_global_discount.pot
odoo/addons/account_global_discount/i18n/es.po
odoo/addons/account_global_discount/i18n/it.po
odoo/addons/account_global_discount/i18n/nl_NL.po
odoo/addons/account_global_discount/i18n/pt.po
odoo/addons/account_global_discount/i18n/sl.po
odoo/addons/account_global_discount/models/__init__.py
odoo/addons/account_global_discount/models/account_move.py
odoo/addons/account_global_discount/models/global_discount.py
odoo/addons/account_global_discount/readme/CONFIGURE.rst
odoo/addons/account_global_discount/readme/CONTRIBUTORS.rst
odoo/addons/account_global_discount/readme/DESCRIPTION.rst
odoo/addons/account_global_discount/readme/ROADMAP.rst
odoo/addons/account_global_discount/readme/USAGE.rst
odoo/addons/account_global_discount/report/__init__.py
odoo/addons/account_global_discount/report/account_invoice_report.py
odoo/addons/account_global_discount/security/ir.model.access.csv
odoo/addons/account_global_discount/security/security.xml
odoo/addons/account_global_discount/static/description/icon.png
odoo/addons/account_global_discount/static/description/icon.svg
odoo/addons/account_global_discount/static/description/index.html
odoo/addons/account_global_discount/tests/__init__.py
odoo/addons/account_global_discount/tests/test_global_discount.py
odoo/addons/account_global_discount/views/account_invoice_views.xml
odoo/addons/account_global_discount/views/global_discount_views.xml
odoo/addons/account_global_discount/views/report_account_invoice.xml
odoo14_addon_account_global_discount-14.0.1.1.0.dist-info/METADATA
odoo14_addon_account_global_discount-14.0.1.1.0.dist-info/WHEEL
odoo14_addon_account_global_discount-14.0.1.1.0.dist-info/top_level.txt
odoo14_addon_account_global_discount-14.0.1.1.0.dist-info/RECORD
